openmimic/__init__.py
openmimic/chartevents.py
openmimic/chartevents_engineering.py
openmimic/cohort.py
openmimic/config.py
openmimic/inputevents_mv.py
openmimic/inputevents_mv_engineering.py
openmimic/labevents.py
openmimic/labevents_engineering.py
openmimic/mimic_preprocessor.py
openmimic/outputevents.py
openmimic/outputevents_engineering.py
openmimic/patient_static.py
openmimic/patient_static_engineering.py
openmimic/utils.py
openmimic-0.0.5.dist-info/METADATA
openmimic-0.0.5.dist-info/WHEEL
openmimic-0.0.5.dist-info/licenses/LICENSE
openmimic-0.0.5.dist-info/RECORD
