Metadata-Version: 2.4
Name: openmimic
Version: 0.0.5
Summary: MIMIC-III preprocessing pipeline to make cohort
Project-URL: Homepage, https://github.com/Harry-PARK/MIMIC_preprocessing
Project-URL: Issues, https://github.com/Harry-PARK/MIMIC_preprocessing/issues
Author-email: Harry_PARK <airroketg@gmail.com>
License-File: LICENSE
Classifier: Operating System :: OS Independent
Classifier: Programming Language :: Python :: 3
Requires-Python: >=3.8
Requires-Dist: numpy
Requires-Dist: pandas
